xcp_esgar/__init__.py
xcp_esgar/cli.py
xcp_esgar/xcp_esgar.py
xcp_esgar-0.0.1.dist-info/METADATA
xcp_esgar-0.0.1.dist-info/WHEEL
xcp_esgar-0.0.1.dist-info/dependency_links.txt
xcp_esgar-0.0.1.dist-info/entry_points.txt
xcp_esgar-0.0.1.dist-info/top_level.txt
xcp_esgar-0.0.1.dist-info/RECORD
