Metadata-Version: 2.1
Name: xcp-esgar
Version: 0.0.1
Summary: A  transformer based Q&A solution for experimentation with BERT - Q&A system based decision processes.
Home-page: https://github.com/rayniervanegmond/xcp_esgar
Author: Raynier van Egmond
Author-email: raynierx@gmail.com
License: UNKNOWN
Keywords: xcp_esgar
Platform: UNKNOWN
Classifier: Development Status :: 2 - Pre-Alpha
Classifier: Intended Audience :: Developers
Classifier: Natural Language :: English
Classifier: Programming Language :: Python :: 3
Classifier: Programming Language :: Python :: 3.5
Classifier: Programming Language :: Python :: 3.6
Classifier: Programming Language :: Python :: 3.7
Classifier: Programming Language :: Python :: 3.8
Requires-Python: >=3.5
Requires-Dist: pytest
Requires-Dist: pytest-runner
